{
  "name": "蘭検定 (初級)",
  "questions": [
    {
      "id": 1,
      "q": "東北地方が北限である、日本産のデンドロビュームの和名は?",
      "answers": [
        {
          "choices": ["ボウラン", "セッコク", "ミヤマムギラン"],
          "ans": 2
        }
      ]
    },
    {
      "id": 2,
      "q": "日当りのよい草むらや芝生などでよく見られる、モジズリというランがあります。そのランの別名は?",
      "answers": [
        {
          "choices": ["クギバナ", "バネバナ", "ネジバナ"],
          "ans": 3
        }
      ]
    },
    {
      "id": 3,
      "q": "花の色がムラサキ色であることから名付けられた、日本にある野生ランは、次のうちどれでしょう。",
      "answers": [
        {
          "choices": ["シラン", "ハクラン", "コクラン"],
          "ans": 1
        }
      ]
    },
    {
      "id": 4,
      "q": "地下部がエビの体を連想させることから和名が付けられた野生ランは、次の内どれでしょう。",
      "answers": [
        {
          "choices": ["カニネ", "イカネ", "エビネ"],
          "ans": 3
        }
      ]
    },
    {
      "id": 5,
      "q": "伊豆七島にのみ自生がみられることから、Calanthe.izu-insularisという学名のランは次のうちどれでしょう。",
      "answers": [
        {
          "choices": ["シマササバラン", "ニオイエビネ", "ハチジョウネッタイラン"],
          "ans": 2
        }
      ]
    },
    {
      "id": 6,
      "q": "千葉県で発見されたことから名付けられた、Ponerorchisは次の内どれ?",
      "answers": [
        {
          "choices": ["キソチドリ", "アワチドリ", "オキナワチドリ"],
          "ans": 2
        }
      ]
    },
    {
      "id": 7,
      "q": "花の色が黄色いことにちなむエビネの、和名は?",
      "answers": [
        {
          "choices": ["キエビネ", "ジエビネ", "キリシマエビネ"],
          "ans": 1
        }
      ]
    },
    {
      "id": 8,
      "q": "サギ (鷺) によく似ていることから名付けられた、野生ランは?",
      "answers": [
        {
          "choices": ["トキソウ", "トンボソウ", "サギソウ"],
          "ans": 3
        }
      ]
    },
    {
      "id": 9,
      "q": "日本の山野にごく普通にみられ、春ラン (シュンラン) という和名で呼ばれているランの属名は?",
      "answers": [
        {
          "choices": ["シンビジューム", "カトレア", "パフィオペディラム"],
          "ans": 1
        }
      ]
    },
    {
      "id": 10,
      "q": "日本で発見されたランの種類はどのくらいでしょうか?",
      "answers": [
        {
          "choices": ["20～30種", "200～300種", "2,000～3,000種"],
          "ans": 2
        }
      ]
    },
    {
      "id": 11,
      "q": "次のうち、ラン科の植物はどれでしょう?",
      "answers": [
        {
          "choices": ["チューリップ", "スイセン", "カトレア"],
          "ans": 3
        },
        {
          "choices": ["シンビジューム", "シクラメン", "ヒマワリ"],
          "ans": 1
        },
        {
          "choices": ["デンドロビューム", "クリスマスローズ", "クレマチス"],
          "ans": 1
        },
        {
          "choices": ["ユリ", "ファレノプシス", "キク"],
          "ans": 2
        },
        {
          "choices": ["バンダ", "スミレ", "バラ"],
          "ans": 1
        },
        {
          "choices": ["イチゴ", "メロン", "バニラ"],
          "ans": 3
        },
        {
          "choices": ["ウツボカズラ", "サラセニア", "パフィオペディラム"],
          "ans": 3
        }
      ]
    },
    {
      "id": 12,
      "q": "ランの球根を使ってできる有名なアイスクリームの名前は?",
      "answers": [
        {
          "choices": ["トルコアイス", "ナタデココ", "シュークリーム"],
          "ans": 1
        }
      ]
    },
    {
      "id": 13,
      "q": "日本に本当にある蘭(ラン科植物),野生ランはどれでしょう?",
      "answers": [
        {
          "choices": ["伊藤蘭", "ウチョウラン", "ホームラン"],
          "ans": 2
        },
        {
          "choices": ["シュンラン", "チャランポラン", "ボブデュラン"],
          "ans": 1
        },
        {
          "choices": ["クスクスラン", "ヤーレンソーラン", "タリラリラン"],
          "ans": 1
        },
        {
          "choices": ["ゴクラクラン", "オキラクラン", "ヨウラクラン"],
          "ans": 3
        }
      ]
    },
    {
      "id": 14,
      "q": "日本に生えているラン科の植物はどれですか?",
      "answers": [
        {
          "choices": ["エビネ", "オモト", "カノンチク"],
          "ans": 1
        },
        {
          "choices": ["クマガイソウ", "ニンジン", "ダイコン"],
          "ans": 1
        },
        {
          "choices": ["ツバメオモト", "サギソウ", "ホトトギス"],
          "ans": 2
        },
        {
          "choices": ["ナデシコ", "アサガオ", "フウラン"],
          "ans": 3
        }
      ]
    },
    {
      "id": 15,
      "q": "日本の野山に自生していないランはどれですか?",
      "answers": [
        {
          "choices": ["オオトリラン", "オオハクウンラン", "オオオサラン"],
          "ans": 1
        },
        {
          "choices": ["ギンラン", "ドウラン", "キンラン"],
          "ans": 2
        }
      ]
    },
    {
      "id": 16,
      "q": "動物や昆虫に似ていることから名付けられた本当にあるランはどれでしょう",
      "answers": [
        {
          "choices": ["ムカデラン", "ゲジゲジラン", "ゴキブリラン"],
          "ans": 1
        },
        {
          "choices": ["タガメソウ", "アメンボソウ", "トンボソウ"],
          "ans": 3
        }
      ]
    },
    {
      "id": 17,
      "q": "日本に自生するシュンランというシンビジュームの別称はどれでしょう?",
      "answers": [
        {
          "choices": ["パパママ", "ジジババ", "オトウカカア"],
          "ans": 2
        },
        {
          "choices": ["エクボ", "ホクロ", "ソバカス"],
          "ans": 2
        }
      ]
    },
    {
      "id": 18,
      "q": "都会の道端などでも見られるランがありますが、次のうちどれでしょう?",
      "answers": [
        {
          "choices": ["タンポポ", "ネコジャラシ", "ネジバナ"],
          "ans": 3
        }
      ]
    },
    {
      "id": 19,
      "q": "日本に自生する野生ランのうち実在するのはどれでしょう?",
      "answers": [
        {
          "choices": ["ホンダヒメラン", "マツダヒメラン", "トヨタヒメラン"],
          "ans": 2
        },
        {
          "choices": ["ワカラン", "シラン", "クダラン"],
          "ans": 2
        },
        {
          "choices": ["ガンゼキラン", "ガンツケラン", "ガングロラン"],
          "ans": 1
        },
        {
          "choices": ["セトウチジャクチョウ", "レブンアツモリ", "アマクサシロウ"],
          "ans": 2
        }
      ]
    },
    {
      "id": 20,
      "q": "小笠原諸島に本当に自生するランはどれでしょう?",
      "answers": [
        {
          "choices": ["アサヒエビネ", "キリンエビネ", "サッポロエビネ"],
          "ans": 1
        }
      ]
    },
    {
      "id": 21,
      "q": "シダの仲間でランと付く植物があります、次のうちどれでしょう?",
      "answers": [
        {
          "choices": ["コブラン", "ヤチラン", "カヤラン"],
          "ans": 1
        }
      ]
    },
    {
      "id": 22,
      "q": "葉を一枚も持たず他の菌の力をかりて生きているランを「無葉のラン」と呼ぶ事がありますが、その中で人物の名前に由来する種はどれでしょう?",
      "answers": [
        {
          "choices": ["トラキチラン", "クマキチラン", "ネコキチラン"],
          "ans": 1
        },
        {
          "choices": ["ヤツデラン", "サカキラン", "アオキラン"],
          "ans": 3
        }
      ]
    },
    {
      "id": 22,
      "q": "葉を全く持たずキノコ類などの菌と共生する事で生きているランは次のうちどれでしょう?",
      "answers": [
        {
          "choices": ["ツチトリモチ", "ツチアケビ", "ツチグリ"],
          "ans": 2
        },
        {
          "choices": ["ギンリョウソウ", "ナヨテンマ", "ナンバンギセル"],
          "ans": 2
        }
      ]
    },
    {
      "id": 23,
      "q": "体の一部を連想させる事から和名となった本当にあるランはどれでしょう?",
      "answers": [
        {
          "choices": ["シラヒゲラン", "アカヒゲラン", "クロヒゲラン"],
          "ans": 1
        },
        {
          "choices": ["ハナゲカヤラン", "マツゲカヤラン", "ワキゲカヤラン"],
          "ans": 2
        }
      ]
    },
    {
      "id": 24,
      "q": "沖縄県の地名に由来する和名が付けられたランはどれでしょう?",
      "answers": [
        {
          "choices": ["イリオモテヒメラン", "イリオモテヤマネコ", "イリオモテマングローブ"],
          "ans": 1
        },
        {
          "choices": ["ヒメギミラン", "オオギミラン", "トノギミラン"],
          "ans": 2
        }
      ]
    },
    {
      "id": 25,
      "q": "神奈川県の温泉地と同じ名前をした実在のランはどれでしょう?",
      "answers": [
        {
          "choices": ["アタミラン", "ハコネラン", "ユガワララン"],
          "ans": 2
        }
      ]
    },
    {
      "id": 26,
      "q": "次のうちランでないのはどれですか?",
      "answers": [
        {
          "choices": ["ホテイアツモリ", "ホテイラン", "ホテイアオイ"],
          "ans": 3
        },
        {
          "choices": ["イラン", "シラン", "ムヨウラン"],
          "ans": 1
        },
        {
          "choices": ["ホシケイラン", "ホシツルラン", "ホシガラス"],
          "ans": 3
        }
      ]
    },
    {
      "id": 27,
      "q": "日本に自生するランの中で着生種(木や岩に着生して生活するラン)はどれでしょう?",
      "answers": [
        {
          "choices": ["セッコク", "ヤドリギ", "ノキシノブ"],
          "ans": 1
        },
        {
          "choices": ["フウラン", "ヒイラギ", "シイノキ"],
          "ans": 1
        }
      ]
    },
    {
      "id": 28,
      "q": "日本に自生する地生種(地面に生えるもの)のランのうち、鳥に由来する名称が付けられているものはどれですか?",
      "answers": [
        {
          "choices": ["カラスノエンドウ", "トキソウ", "スズメノテッポウ"],
          "ans": 2
        },
        {
          "choices": ["カラスウリ", "カモメラン", "スズメノカタビラ"],
          "ans": 2
        }
      ]
    },
    {
      "id": 29,
      "q": "地名が元になり、名前が付けられた実在する地生ラン(地面に生えるラン)はどれでしょう?",
      "answers": [
        {
          "choices": ["リュウキュウエビネ", "リュウキュウアセビ", "リュキュウツツジ"],
          "ans": 1
        },
        {
          "choices": ["セタガヤシラン", "エドガワシラン", "コウトウシラン"],
          "ans": 3
        }
      ]
    },
    {
      "id": 30,
      "q": "日本の山にちなむ和名をもつランはどれでしょう?",
      "answers": [
        {
          "choices": ["オモトダケエビネ", "カツウダケエビネ", "コミダケエビネ"],
          "ans": 2
        },
        {
          "choices": ["ガッサンチドリ", "ユドノチドリ", "チョウカイチドリ"],
          "ans": 1
        }
      ]
    },
    {
      "id": 31,
      "q": "本当に日本にある変わった名前のランはどれでしょう?",
      "answers": [
        {
          "choices": ["オニノカクラン", "オニノヤガラ", "オニノカナボウ"],
          "ans": 2
        },
        {
          "choices": ["ムラサキツユクサ", "ムラサキケマン", "ムラサキチュウガエリ"],
          "ans": 3
        },
         {
          "choices": ["ゴクラクトンボ", "シオカラトンボ", "ツブラトンボ"],
          "ans": 3
        }
      ]
    },
    {
      "id": 32,
      "q": "うそのようで本当にあるランはどれでしょう?",
      "answers": [
        {
          "choices": ["ハクホウシュスラン", "アケボノシュスラン", "コニシキシュスラン"],
          "ans": 2
        }
      ]
    },
    {
      "id": 33,
      "q": "日本に自生するラン科植物はどれですか?",
      "answers": [
        {
          "choices": ["ミズバショウ", "ミズチドリ", "ミズスマシ"],
          "ans": 2
        },
        {
          "choices": ["オオイヌノフグリ", "オオバギボウシ", "オオバノトンボソウ"],
          "ans": 3
        },
         {
          "choices": ["アマミセイシカ", "アマミノクロウサギ", "アマミトンボ"],
          "ans": 3
        }
      ]
    },
    {
      "id": 34,
      "q": "花の色に由来することから名前がつけられた日本のランはどれでしょう?",
      "answers": [
        {
          "choices": ["キバナコクラン", "シロバナコクラン", "クロバナキラン"],
          "ans": 1
        },
        {
          "choices": ["シラン", "ヒラン", "キラン"],
          "ans": 1
        }
      ]
    },
    {
      "id": 35,
      "q": "日本の野山に生える実在の野生ランはどれですか?",
      "answers": [
        {
          "choices": ["アツギムヨウラン", "ウスギムヨウラン", "キブクレムヨウラン"],
          "ans": 2
        },
        {
          "choices": ["ジャノメラン", "アニメラン", "カゴメラン", "アミメラン"],
          "ans": 3
        }
      ]
    },
    {
      "id": 36,
      "q": "日本の地名に由来するランで本当にあるランはどれですか?",
      "answers": [
        {
          "choices": ["オゼノヤマトンボ", "オゼサワトノンボ", "オゼノハラトンボ"],
          "ans": 2
        }
      ]
    },
    {
      "id": 37,
      "q": "日本の野生ランのうち実在の着生種(木や岩に着生して生育している)はどれですか?",
      "answers": [
        {
          "choices": ["キバナセッコク", "キバナコッセツ", "キバナダッキュウ"],
          "ans": 1
        },
        {
          "choices": ["シクシクラン", "メソメソラン", "クスクスラン"],
          "ans": 3
        },
        {
          "choices": ["オイラン", "クモラン", "ドッグラン"],
          "ans": 2
        }
      ]
    },
    {
      "id": 38,
      "q": "日本にある島で発見されたことで、その島にちなむ和名が付けられているランはどれでしょう?",
      "answers": [
        {
          "choices": ["マダガスカルエビネ", "トクノシマエビネ", "ハワイアンエビネ"],
          "ans": 2
        },
        {
          "choices": ["ハチジョウネッタイラン", "ハチジョウコジマ", "ハチジョウジマノキョン"],
          "ans": 1
        },
        {
          "choices": ["ガラパゴスクジャク", "オキナワチドリ", "ミクロネシアハチドリ"],
          "ans": 2
        },
        {
          "choices": ["ボルネオネッタイラン", "ヤクシマネッタイラン", "スマトラネッタイラン"],
          "ans": 2
        }
      ]
    },
    {
      "id": 39,
      "q": "良い香りがすることから名付けられた日本の野生ランは?",
      "answers": [
        {
          "choices": ["ジャコウヌキラン", "ジンチョウゲ", "キンモクセイ"],
          "ans": 1
        },
        {
          "choices": ["ニオイエビネ", "ドクダミ", "ヘクソカズラ"],
          "ans": 1
        }
      ]
    },
    {
      "id": 40,
      "q": "発見地からサツマチドリという名前が付けられたランがありますが、その自生地はどこの県ですか?",
      "answers": [
        {
          "choices": ["鹿児島県", "熊本県", "宮崎県"],
          "ans": 1
        }
      ]
    },
    {
      "id": 41,
      "q": "トクノシマエビネが自生する場所はどこの都道府県ですか?",
      "answers": [
        {
          "choices": ["徳島県", "熊本県", "鹿児島県"],
          "ans": 3
        }
      ]
    },
    {
      "id": 42,
      "q": "ハチジョウツレサギ(ソウ)はどこの都道府県に自生していますか?",
      "answers": [
        {
          "choices": ["東京都", "静岡県", "鹿児島県", "沖縄県"],
          "ans": 1
        }
      ]
    },
    {
      "id": 43,
      "q": "小笠原諸島固有のラン(小笠原諸島だけに自生しているラン)はどれでしょう?",
      "answers": [
        {
          "choices": ["オガサワラトカゲ", "オガサワラオオコウモリ", "オガサワラシコウラン"],
          "ans": 3
        },
        {
          "choices": ["ハハジマメグロ", "ハハジマノボタン", "ハハジマホザキラン"],
          "ans": 3
        }
      ]
    },
    {
      "id": 44,
      "q": "日本に自生するランのうち本当にある地生ラン(地面の中に根を伸ばして生活するラン)はどれでしょう?",
      "answers": [
        {
          "choices": ["シュスラン", "ミシュラン", "モンブラン", "イザマイラン"],
          "ans": 1
        },
        {
          "choices": ["ヤブコウジラン", "ヤブミョウガラン", "ヤブガラシラン", "ヤブイシャラン"],
          "ans": 2
        }
      ]
    },
    {
      "id": 45,
      "q": "アツモリソウやクマガイソウなどシプリペジュームの語源は誰かのはきものに由来すると言われていますが、次のうちどれでしょう?",
      "answers": [
        {
          "choices": ["女神のスリッパ", "悪魔のながぐつ", "鬼のぞうり", "閻魔様のハイヒール"],
          "ans": 1
        }
      ]
    },
    {
      "id": 46,
      "q": "エビネの属名=カランセにはギリシャ語がもととなるある意味がありますが、次のうちどれでしょう?",
      "answers": [
        {
          "choices": ["美しい花", "ブサイクな男", "いたずら小僧"],
          "ans": 1
        }
      ]
    },
    {
      "id": 47,
      "q": "次のうち本当にある日本に自生しているランはどれでしょう?",
      "answers": [
        {
          "choices": ["ヒロハノカラン", "イッシンフラン", "デンキブラン"],
          "ans": 1
        },
        {
          "choices": ["ヒメトケンラン", "リコウラン", "ゴウカケンラン"],
          "ans": 1
        }
      ]
    },
    {
      "id": 48,
      "q": "次のうち神奈川県の地名と同じ名前をもつ実在のランはどれでしょう",
      "answers": [
        {
          "choices": ["エノシマラン", "クゲヌマラン", "オオイソラン", "フジサワラン"],
          "ans": 2
        }
      ]
    },
    {
      "id": 49,
      "q": "日本には良い香りがする野生のシンビジュームの仲間があります。次のうちどれでしょう? ",
      "answers": [
        {
          "choices": ["カンラン", "カンレイシャ", "カンランシャ"],
          "ans": 1
        }
      ]
    },
    {
      "id": 50,
      "q": "日本に自生するシンビジュームの仲間シュンランの別名は? ",
      "answers": [
        {
          "choices": ["ジジババ", "ネコババ", "アリババ"],
          "ans": 1
        }
      ]
    },
    {
      "id": 51,
      "q": "体の一部を連想させることから名付けられた本当にある地生ランはどれですか? ",
      "answers": [
        {
          "choices": ["テガタチドリ", "アシガタチドリ", "シリガタチドリ"],
          "ans": 1
        }
      ]
    },
    {
      "id": 52,
      "q": "葉ももたず他の菌と共生して生きている実存のランはどれですか? ",
      "answers": [
        {
          "choices": ["サカネラン", "サキナラン", "サクヨラン"],
          "ans": 1
        }
      ]
    },
    {
      "id": 53,
      "q": "日本に本当に自生する地生ランはどれですか? ",
      "answers": [
        {
          "choices": ["ミスズラン", "ミミズラン", "ミミズクラン"],
          "ans": 1
        },
        {
          "choices": ["タカツルラン", "ウグイズノタニワタリラン", "トンビニアブラゲラン"],
          "ans": 1
        },
        {
          "choices": ["マイサギソウ", "ユウサギソウ", "ミイサギソウ"],
          "ans": 1
        },
        {
          "choices": ["トサカメオトラン", "オシドリフウフラン", "スズメノキョウダイラン"],
          "ans": 1
        },
        {
          "choices": ["コンジキヤガラ", "ショウジキヤガラ", "ウソツキヤガラ"],
          "ans": 1
        },
        {
          "choices": ["アサヒラン", "エビスラン", "オリオンラン", "サントリラン"],
          "ans": 1
        }
      ]
    },
    {
      "id": 54,
      "q": "日本には葉をまったくもたない無葉のランがありますが、実在しないランはどれですか? ",
      "answers": [
        {
          "choices": ["ゴイケンムヨウラン", "クロムヨウラン", "ムラサキムヨウラン", "ウスギムヨウラン"],
          "ans": 1
        }
      ]
    },
    {
      "id": 55,
      "q": "岩場などに多く見られることから名付けられた野生ランはどれでしょう? ",
      "answers": [
        {
          "choices": ["イワチドリ", "イワシャジン", "イワタバコ"],
          "ans": 1
        }
      ]
    },
    {
      "id": 56,
      "q": "日本に自生するシンビジュームの仲間はどれでしょう? ",
      "answers": [
        {
          "choices": ["アマクサコラン", "サシスセソラン", "ハヒフヘホラン", "ナニヌネノラン"],
          "ans": 1
        }
      ]
    },
    {
      "id": 57,
      "q": "日本にある島で発見されたことから名付けられたランの仲間はどれですか? ",
      "answers": [
        {
          "choices": ["オガサワラシュスラン", "オニガシマシコウラン", "タカラジマヨウラクラン"],
          "ans": 1
        }
      ]
    },
    {
      "id": 58,
      "q": "伊豆七島に多く自生することから名付けられた実在の地生ランはどれでしょう? ",
      "answers": [
        {
          "choices": ["ハチジョウシュスラン", "ロクジョウシュスラン", "ジュウジョウシュスラン"],
          "ans": 1
        }
      ]
    },
    {
      "id": 59,
      "q": "ラン科以外の植物に似ていることから名前が付けられた実在の野生ランはどれですか? ",
      "answers": [
        {
          "choices": ["イモネヤガラ", "ユリネヤガラ", "エビネヤガラ"],
          "ans": 1
        }
      ]
    },
    {
      "id": 60,
      "q": "小笠原諸島の固有種 (小笠原諸島にだけ自生する) のランはどれですか? ",
      "answers": [
        {
          "choices": ["シマツレサギソウ", "ムニンノボタン", "タコノキ", "ハカラメ"],
          "ans": 1
        }
      ]
    },
    {
      "id": 61,
      "q": "末尾にランとつくがラン科ではない植物はどれですか? ",
      "answers": [
        {
          "choices": ["キミガヨラン", "サイハイラン", "ムヨウラン"],
          "ans": 1
        },
        {
          "choices": ["ドイツスズラン", "ギンラン", "キンラン"],
          "ans": 1
        }
      ]
    },
    {
      "id": 62,
      "q": "日本に本当に自生するエビネはどれですか? ",
      "answers": [
        {
          "choices": ["サルメンエビネ", "イヌメンエビネ", "ネコメンエビネ", "トラメンエビネ"],
          "ans": 1
        },
        {
          "choices": ["キンセイラン", "カセイラン", "モクセイラン"],
          "ans": 1
        }
      ]
    },
    {
      "id": 63,
      "q": "エビネの仲間を意味する属名 (世界共通名) は次のうちどれですか? ",
      "answers": [
        {
          "choices": ["カランセ", "カラジューム", "カランコエ", "カランコロン"],
          "ans": 1
        }
      ]
    },
    {
      "id": 64,
      "q": "限られた地域にだけ自生する固有種といわれているランがありますが、その固有種のサツマチドリの自生地はどれでしょう? ",
      "answers": [
        {
          "choices": ["鹿児島県", "熊本県", "大分県"],
          "ans": 1
        }
      ]
    },
    {
      "id": 65,
      "q": "限られた地域にだけ自生する固有種といわれているランがありますが、その固有種のハハジマホザキランの自生地はどれでしょう? ",
      "answers": [
        {
          "choices": ["東京都", "広島県", "鹿児島県"],
          "ans": 1
        }
      ]
    },
    {
      "id": 66,
      "q": "限られた地域にだけ自生する固有種といわれているランがありますが、その固有種のオガサワラシコウランの自生地はどれでしょう? ",
      "answers": [
        {
          "choices": ["東京都", "新潟県", "宮崎県"],
          "ans": 1
        }
      ]
    },
    {
      "id": 67,
      "q": "限られた地域にだけ自生する固有種といわれているランがありますが、その固有種のレブンアツモリソウの自生地はどれでしょう? ",
      "answers": [
        {
          "choices": ["北海道", "沖縄県", "長崎県"],
          "ans": 1
        }
      ]
    },
    {
      "id": 68,
      "q": "伊豆七島の固有種ニオイエビネの自生地はどこでしょう? ",
      "answers": [
        {
          "choices": ["東京都", "北海道", "大阪府"],
          "ans": 1
        }
      ]
    },
    {
      "id": 69,
      "q": "佐賀県の固有種であるクロカミランの自生地はどこでしょう? ",
      "answers": [
        {
          "choices": ["九州", "四国", "沖縄県"],
          "ans": 1
        }
      ]
    },
    {
      "id": 70,
      "q": "房総半島の固有種アワチドリの自生地はどこでしょう? ",
      "answers": [
        {
          "choices": ["千葉県", "徳島県", "和歌山県"],
          "ans": 1
        }
      ]
    },
    {
      "id": 71,
      "q": "実在する日本の着生ラン（樹や岩に着生して生えるラン）はどれですか? ",
      "answers": [
        {
          "choices": ["クスクスラン", "ヒソヒソラン", "ドキドキラン", "ワクワクラン"],
          "ans": 1
        },
        {
          "choices": ["カヤラン", "ファミリーレストラン", "ケシカラン"],
          "ans": 1
        },
        {
          "choices": ["ムカデラン", "ブーメラン", "ザックバラン"],
          "ans": 1
        }
      ]
    },
    {
      "id": 72,
      "q": "東京よりも南に自生しているラン科植物はどれですか? ",
      "answers": [
        {
          "choices": ["オオオサラン", "オオオニバス", "オオウバユリ"],
          "ans": 1
        }
      ]
    },
    {
      "id": 73,
      "q": "次のうちラン科植物はどれですか? ",
      "answers": [
        {
          "choices": ["バンダ", "キリン", "タヌキ"],
          "ans": 1
        },
        {
          "choices": ["ミズトンボ", "アカトンボ", "イトトンボ"],
          "ans": 1
        },
        {
          "choices": ["ミズチドリ", "ミズカマキリ", "ミズスマシ"],
          "ans": 1
        },
        {
          "choices": ["ミヤマウズラ", "ミヤマリンドウ", "ミヤマクワガタ"],
          "ans": 1
        },
        {
          "choices": ["クマガイソウ", "ブタノマンジュウ", "キツネノカミソリ"],
          "ans": 1
        }
      ]
    },
    {
      "id": 74,
      "q": "鹿児島県で発見されたことで名付けられたエビネは? ",
      "answers": [
        {
          "choices": ["サクラジマエビネ", "キソエビネ", "オキナワエビネ"],
          "ans": 1
        }
      ]
    },
    {
      "id": 75,
      "q": "鹿児島県の島に由来する和名をもつエビネは次のうちどれですか? ",
      "answers": [
        {
          "choices": ["トクノシマエビネ", "オクシリエビネ", "レブンエビネ"],
          "ans": 1
        }
      ]
    },
    {
      "id": 76,
      "q": "アマミエビネという和名はどこの島に由来しますか? ",
      "answers": [
        {
          "choices": ["奄美大島", "伊豆大島", "式根島"],
          "ans": 1
        }
      ]
    },
    {
      "id": 77,
      "q": "レブンアツモリソウは次のうちどこの島に自生していますか? ",
      "answers": [
        {
          "choices": ["礼文島", "八丈島", "対馬"],
          "ans": 1
        }
      ]
    },
    {
      "id": 78,
      "q": "伊豆諸島の固有種ニオイエビネはどこの都道府県に自生していますか? ",
      "answers": [
        {
          "choices": ["東京都", "長崎県", "沖縄県"],
          "ans": 1
        }
      ]
    },
    {
      "id": 79,
      "q": "キンコンカン実在しないのはどれですか? ",
      "answers": [
        {
          "choices": ["コンラン", "キンラン", "カンラン"],
          "ans": 1
        }
      ]
    },
    {
      "id": 80,
      "q": "実在しないランはどれですか? ",
      "answers": [
        {
          "choices": ["ヤマンバ", "ヤマトキソウ", "ヤマザキソウ"],
          "ans": 1
        }
      ]
    }
  ]
}
